<annotation>
	<folder>my-project-name</folder>
	<filename>s194.PNG</filename>
	<path>/my-project-name/s194.PNG</path>
	<source>
		<database>Unspecified</database>
	</source>
	<size>
		<width>231</width>
		<height>343</height>
		<depth>3</depth>
	</size>
	<object>
		<name>Occupied</name>
		<pose>Unspecified</pose>
		<truncated>0</truncated>
		<difficult>0</difficult>
		<bndbox>
			<xmin>58</xmin>
			<ymin>7</ymin>
			<xmax>164</xmax>
			<ymax>64</ymax>
		</bndbox>
	</object>
	<object>
		<name>Occupied</name>
		<pose>Unspecified</pose>
		<truncated>0</truncated>
		<difficult>0</difficult>
		<bndbox>
			<xmin>58</xmin>
			<ymin>64</ymin>
			<xmax>164</xmax>
			<ymax>126</ymax>
		</bndbox>
	</object>
	<object>
		<name>Occupied</name>
		<pose>Unspecified</pose>
		<truncated>0</truncated>
		<difficult>0</difficult>
		<bndbox>
			<xmin>57</xmin>
			<ymin>125</ymin>
			<xmax>163</xmax>
			<ymax>186</ymax>
		</bndbox>
	</object>
	<object>
		<name>Vacant</name>
		<pose>Unspecified</pose>
		<truncated>0</truncated>
		<difficult>0</difficult>
		<bndbox>
			<xmin>57</xmin>
			<ymin>186</ymin>
			<xmax>163</xmax>
			<ymax>244</ymax>
		</bndbox>
	</object>
</annotation>