<annotation>
	<folder>my-project-name</folder>
	<filename>s294.PNG</filename>
	<path>/my-project-name/s294.PNG</path>
	<source>
		<database>Unspecified</database>
	</source>
	<size>
		<width>309</width>
		<height>294</height>
		<depth>3</depth>
	</size>
	<object>
		<name>Vacant</name>
		<pose>Unspecified</pose>
		<truncated>0</truncated>
		<difficult>0</difficult>
		<bndbox>
			<xmin>7</xmin>
			<ymin>9</ymin>
			<xmax>81</xmax>
			<ymax>150</ymax>
		</bndbox>
	</object>
	<object>
		<name>Occupied</name>
		<pose>Unspecified</pose>
		<truncated>0</truncated>
		<difficult>0</difficult>
		<bndbox>
			<xmin>77</xmin>
			<ymin>9</ymin>
			<xmax>154</xmax>
			<ymax>147</ymax>
		</bndbox>
	</object>
	<object>
		<name>Occupied</name>
		<pose>Unspecified</pose>
		<truncated>0</truncated>
		<difficult>0</difficult>
		<bndbox>
			<xmin>152</xmin>
			<ymin>9</ymin>
			<xmax>227</xmax>
			<ymax>149</ymax>
		</bndbox>
	</object>
	<object>
		<name>Vacant</name>
		<pose>Unspecified</pose>
		<truncated>0</truncated>
		<difficult>0</difficult>
		<bndbox>
			<xmin>227</xmin>
			<ymin>9</ymin>
			<xmax>301</xmax>
			<ymax>150</ymax>
		</bndbox>
	</object>
	<object>
		<name>Vacant</name>
		<pose>Unspecified</pose>
		<truncated>0</truncated>
		<difficult>0</difficult>
		<bndbox>
			<xmin>7</xmin>
			<ymin>150</ymin>
			<xmax>81</xmax>
			<ymax>288</ymax>
		</bndbox>
	</object>
	<object>
		<name>Vacant</name>
		<pose>Unspecified</pose>
		<truncated>0</truncated>
		<difficult>0</difficult>
		<bndbox>
			<xmin>80</xmin>
			<ymin>147</ymin>
			<xmax>155</xmax>
			<ymax>288</ymax>
		</bndbox>
	</object>
	<object>
		<name>Vacant</name>
		<pose>Unspecified</pose>
		<truncated>0</truncated>
		<difficult>0</difficult>
		<bndbox>
			<xmin>155</xmin>
			<ymin>148</ymin>
			<xmax>229</xmax>
			<ymax>288</ymax>
		</bndbox>
	</object>
	<object>
		<name>Vacant</name>
		<pose>Unspecified</pose>
		<truncated>0</truncated>
		<difficult>0</difficult>
		<bndbox>
			<xmin>229</xmin>
			<ymin>149</ymin>
			<xmax>303</xmax>
			<ymax>287</ymax>
		</bndbox>
	</object>
</annotation>