<annotation>
	<folder>my-project-name</folder>
	<filename>s137.PNG</filename>
	<path>/my-project-name/s137.PNG</path>
	<source>
		<database>Unspecified</database>
	</source>
	<size>
		<width>188</width>
		<height>294</height>
		<depth>3</depth>
	</size>
	<object>
		<name>Vacant</name>
		<pose>Unspecified</pose>
		<truncated>0</truncated>
		<difficult>0</difficult>
		<bndbox>
			<xmin>29</xmin>
			<ymin>219</ymin>
			<xmax>158</xmax>
			<ymax>289</ymax>
		</bndbox>
	</object>
	<object>
		<name>Occupied</name>
		<pose>Unspecified</pose>
		<truncated>0</truncated>
		<difficult>0</difficult>
		<bndbox>
			<xmin>29</xmin>
			<ymin>151</ymin>
			<xmax>157</xmax>
			<ymax>219</ymax>
		</bndbox>
	</object>
	<object>
		<name>Occupied</name>
		<pose>Unspecified</pose>
		<truncated>0</truncated>
		<difficult>0</difficult>
		<bndbox>
			<xmin>29</xmin>
			<ymin>82</ymin>
			<xmax>158</xmax>
			<ymax>152</ymax>
		</bndbox>
	</object>
	<object>
		<name>Vacant</name>
		<pose>Unspecified</pose>
		<truncated>0</truncated>
		<difficult>0</difficult>
		<bndbox>
			<xmin>29</xmin>
			<ymin>13</ymin>
			<xmax>158</xmax>
			<ymax>83</ymax>
		</bndbox>
	</object>
</annotation>