<annotation>
	<folder>my-project-name</folder>
	<filename>s185.PNG</filename>
	<path>/my-project-name/s185.PNG</path>
	<source>
		<database>Unspecified</database>
	</source>
	<size>
		<width>336</width>
		<height>86</height>
		<depth>3</depth>
	</size>
	<object>
		<name>Vacant</name>
		<pose>Unspecified</pose>
		<truncated>0</truncated>
		<difficult>0</difficult>
		<bndbox>
			<xmin>10</xmin>
			<ymin>7</ymin>
			<xmax>46</xmax>
			<ymax>77</ymax>
		</bndbox>
	</object>
	<object>
		<name>Vacant</name>
		<pose>Unspecified</pose>
		<truncated>0</truncated>
		<difficult>0</difficult>
		<bndbox>
			<xmin>46</xmin>
			<ymin>7</ymin>
			<xmax>82</xmax>
			<ymax>77</ymax>
		</bndbox>
	</object>
	<object>
		<name>Vacant</name>
		<pose>Unspecified</pose>
		<truncated>0</truncated>
		<difficult>0</difficult>
		<bndbox>
			<xmin>82</xmin>
			<ymin>8</ymin>
			<xmax>117</xmax>
			<ymax>77</ymax>
		</bndbox>
	</object>
	<object>
		<name>Vacant</name>
		<pose>Unspecified</pose>
		<truncated>0</truncated>
		<difficult>0</difficult>
		<bndbox>
			<xmin>117</xmin>
			<ymin>7</ymin>
			<xmax>153</xmax>
			<ymax>77</ymax>
		</bndbox>
	</object>
	<object>
		<name>Vacant</name>
		<pose>Unspecified</pose>
		<truncated>0</truncated>
		<difficult>0</difficult>
		<bndbox>
			<xmin>153</xmin>
			<ymin>7</ymin>
			<xmax>188</xmax>
			<ymax>77</ymax>
		</bndbox>
	</object>
	<object>
		<name>Vacant</name>
		<pose>Unspecified</pose>
		<truncated>0</truncated>
		<difficult>0</difficult>
		<bndbox>
			<xmin>187</xmin>
			<ymin>6</ymin>
			<xmax>224</xmax>
			<ymax>76</ymax>
		</bndbox>
	</object>
	<object>
		<name>Vacant</name>
		<pose>Unspecified</pose>
		<truncated>0</truncated>
		<difficult>0</difficult>
		<bndbox>
			<xmin>223</xmin>
			<ymin>6</ymin>
			<xmax>258</xmax>
			<ymax>76</ymax>
		</bndbox>
	</object>
	<object>
		<name>Vacant</name>
		<pose>Unspecified</pose>
		<truncated>0</truncated>
		<difficult>0</difficult>
		<bndbox>
			<xmin>257</xmin>
			<ymin>6</ymin>
			<xmax>293</xmax>
			<ymax>75</ymax>
		</bndbox>
	</object>
	<object>
		<name>Vacant</name>
		<pose>Unspecified</pose>
		<truncated>0</truncated>
		<difficult>0</difficult>
		<bndbox>
			<xmin>293</xmin>
			<ymin>7</ymin>
			<xmax>329</xmax>
			<ymax>75</ymax>
		</bndbox>
	</object>
</annotation>