<annotation>
	<folder>my-project-name</folder>
	<filename>s334.PNG</filename>
	<path>/my-project-name/s334.PNG</path>
	<source>
		<database>Unspecified</database>
	</source>
	<size>
		<width>284</width>
		<height>183</height>
		<depth>3</depth>
	</size>
	<object>
		<name>Vacant</name>
		<pose>Unspecified</pose>
		<truncated>0</truncated>
		<difficult>0</difficult>
		<bndbox>
			<xmin>5</xmin>
			<ymin>15</ymin>
			<xmax>72</xmax>
			<ymax>163</ymax>
		</bndbox>
	</object>
	<object>
		<name>Occupied</name>
		<pose>Unspecified</pose>
		<truncated>0</truncated>
		<difficult>0</difficult>
		<bndbox>
			<xmin>71</xmin>
			<ymin>15</ymin>
			<xmax>140</xmax>
			<ymax>163</ymax>
		</bndbox>
	</object>
	<object>
		<name>Occupied</name>
		<pose>Unspecified</pose>
		<truncated>0</truncated>
		<difficult>0</difficult>
		<bndbox>
			<xmin>140</xmin>
			<ymin>15</ymin>
			<xmax>209</xmax>
			<ymax>163</ymax>
		</bndbox>
	</object>
	<object>
		<name>Occupied</name>
		<pose>Unspecified</pose>
		<truncated>0</truncated>
		<difficult>0</difficult>
		<bndbox>
			<xmin>209</xmin>
			<ymin>16</ymin>
			<xmax>270</xmax>
			<ymax>163</ymax>
		</bndbox>
	</object>
</annotation>