<annotation>
	<folder>my-project-name</folder>
	<filename>s379.PNG</filename>
	<path>/my-project-name/s379.PNG</path>
	<source>
		<database>Unspecified</database>
	</source>
	<size>
		<width>223</width>
		<height>296</height>
		<depth>3</depth>
	</size>
	<object>
		<name>Vacant</name>
		<pose>Unspecified</pose>
		<truncated>0</truncated>
		<difficult>0</difficult>
		<bndbox>
			<xmin>57</xmin>
			<ymin>4</ymin>
			<xmax>191</xmax>
			<ymax>79</ymax>
		</bndbox>
	</object>
	<object>
		<name>Occupied</name>
		<pose>Unspecified</pose>
		<truncated>0</truncated>
		<difficult>0</difficult>
		<bndbox>
			<xmin>55</xmin>
			<ymin>78</ymin>
			<xmax>191</xmax>
			<ymax>149</ymax>
		</bndbox>
	</object>
	<object>
		<name>Occupied</name>
		<pose>Unspecified</pose>
		<truncated>0</truncated>
		<difficult>0</difficult>
		<bndbox>
			<xmin>55</xmin>
			<ymin>149</ymin>
			<xmax>191</xmax>
			<ymax>220</ymax>
		</bndbox>
	</object>
	<object>
		<name>Occupied</name>
		<pose>Unspecified</pose>
		<truncated>0</truncated>
		<difficult>0</difficult>
		<bndbox>
			<xmin>54</xmin>
			<ymin>219</ymin>
			<xmax>191</xmax>
			<ymax>287</ymax>
		</bndbox>
	</object>
</annotation>